README.md
setup.py
distributions192/Binomialdistribution.py
distributions192/Gaussiandistribution.py
distributions192/Generaldistribution.py
distributions192/__init__.py
distributions192.egg-info/PKG-INFO
distributions192.egg-info/SOURCES.txt
distributions192.egg-info/dependency_links.txt
distributions192.egg-info/not-zip-safe
distributions192.egg-info/top_level.txt